cache.py
cacheado-1.4.2.dist-info/licenses/LICENSE
protocols/__init__.py
protocols/storage_provider.py
protocols/storage_rule.py
storages/__init__.py
storages/in_memory.py
storages/mongodb.py
storages/redis.py
storages/rule_aware_storage.py
storages/rules/__init__.py
storages/rules/lifetime_evict.py
storages/rules/lru_evict.py
storages/rules/max_items_evict.py
cacheado-1.4.2.dist-info/METADATA
cacheado-1.4.2.dist-info/WHEEL
cacheado-1.4.2.dist-info/top_level.txt
cacheado-1.4.2.dist-info/RECORD
