Metadata-Version: 2.4
Name: cacheado
Version: 1.4.2
Summary: Advanced Python cache system with multi-tenant support, scope hierarchies, and configurable eviction policies
Author-email: George Mendonca Silva de Morais <george1bsilva@outlook.com>
License-Expression: MIT
Project-URL: Homepage, https://github.com/GeorgeOgeorge/cacheado
Project-URL: Repository, https://github.com/GeorgeOgeorge/cacheado
Project-URL: Documentation, https://github.com/GeorgeOgeorge/cacheado#readme
Project-URL: Bug Tracker, https://github.com/GeorgeOgeorge/cacheado/issues
Keywords: cache,multi-tenant,hierarchical,eviction,thread-safe
Classifier: Development Status :: 5 - Production/Stable
Classifier: Intended Audience :: Developers
Classifier: Operating System :: OS Independent
Classifier: Programming Language :: Python :: 3
Classifier: Programming Language :: Python :: 3.9
Classifier: Programming Language :: Python :: 3.10
Classifier: Programming Language :: Python :: 3.11
Classifier: Programming Language :: Python :: 3.12
Classifier: Topic :: Software Development :: Libraries :: Python Modules
Requires-Python: >=3.9
License-File: LICENSE
Provides-Extra: redis
Requires-Dist: redis[asyncio]>=5.0.0; extra == "redis"
Provides-Extra: memcached
Requires-Dist: pymemcache>=4.0.0; extra == "memcached"
Provides-Extra: mongodb
Requires-Dist: pymongo>=4.10.1; extra == "mongodb"
Provides-Extra: all
Requires-Dist: redis[asyncio]>=5.0.0; extra == "all"
Requires-Dist: pymemcache>=4.0.0; extra == "all"
Requires-Dist: pymongo>=4.10.1; extra == "all"
Provides-Extra: dev
Requires-Dist: pytest>=7.0.0; extra == "dev"
Requires-Dist: pytest-cov>=4.0.0; extra == "dev"
Requires-Dist: pytest-asyncio>=0.21.0; extra == "dev"
Requires-Dist: flake8>=6.0.0; extra == "dev"
Requires-Dist: black>=23.0.0; extra == "dev"
Requires-Dist: isort>=5.12.0; extra == "dev"
Requires-Dist: mypy>=1.0.0; extra == "dev"
Requires-Dist: pre-commit>=3.0.0; extra == "dev"
Dynamic: license-file
